climdex/__init__.py
climdex/precipitation.py
climdex/temperature.py
climdex/utils.py
pyclimdex-0.0.1.dist-info/LICENSE
pyclimdex-0.0.1.dist-info/METADATA
pyclimdex-0.0.1.dist-info/WHEEL
pyclimdex-0.0.1.dist-info/top_level.txt
pyclimdex-0.0.1.dist-info/RECORD
